lmgeo/__init__.py
lmgeo/run_tests.py
lmgeo/formats/__init__.py
lmgeo/formats/asciigrid.py
lmgeo/formats/auxiliaryfile.py
lmgeo/formats/bandraster.py
lmgeo/formats/basetiffraster.py
lmgeo/formats/bilraster.py
lmgeo/formats/bitmapraster.py
lmgeo/formats/bsqraster.py
lmgeo/formats/const.py
lmgeo/formats/csfraster.py
lmgeo/formats/floatingpointraster.py
lmgeo/formats/geotiffraster.py
lmgeo/formats/gridenvelope2d.py
lmgeo/formats/hdf5raster.py
lmgeo/formats/inmemoryraster.py
lmgeo/formats/netcdf4envelope2d.py
lmgeo/formats/netcdf4raster.py
lmgeo/formats/numpyraster.py
lmgeo/formats/pngraster.py
lmgeo/formats/raster.py
lmgeo/formats/rioraster.py
lmgeo/formats/rowtiffraster.py
lmgeo/formats/striptiffraster.py
lmgeo/formats/tiletiffraster.py
lmgeo/formats/webpraster.py
lmgeo/formats/worldfile.py
lmgeo/tests/__init__.py
lmgeo/tests/__main__.py
lmgeo/tests/context.py
lmgeo/tests/prepare_testdata.py
lmgeo/tests/test_asciigrid.py
lmgeo/tests/test_baseraster.py
lmgeo/tests/test_bilraster.py
lmgeo/tests/test_bitmapraster.py
lmgeo/tests/test_bsqraster.py
lmgeo/tests/test_clump.py
lmgeo/tests/test_csfraster.py
lmgeo/tests/test_floatingpointraster.py
lmgeo/tests/test_numpyraster.py
lmgeo/tests/test_rioraster.py
lmgeo/tests/test_rowtiffraster.py
lmgeo/toolbox/__init__.py
lmgeo/toolbox/cliplib.py
lmgeo/toolbox/copylib.py
lmgeo/toolbox/grouplib.py
lmgeo/toolbox/mapalg.py
lmgeo/toolbox/mapplotlib.py
lmgeo/toolbox/punchlib.py
lmgeo/toolbox/remaplib.py
lmgeo/toolbox/scalelib.py
lmgeo/toolbox/striplib.py
lmgeo/toolbox/tilelib.py
lmgeo/toolbox/vcliplib.py
lmgeo/toolbox/vectorlib.py
lmgeo/toolbox/conversion/__init__.py
lmgeo/toolbox/conversion/reproject.py
lmgeo/toolbox/conversion/vectorise.py
Lmgeo-1.1.0.dist-info/LICENSE
Lmgeo-1.1.0.dist-info/METADATA
Lmgeo-1.1.0.dist-info/WHEEL
Lmgeo-1.1.0.dist-info/top_level.txt
Lmgeo-1.1.0.dist-info/RECORD
