Metadata-Version: 2.1
Name: Lmgeo
Version: 1.1.0
Summary: Python raster GIS library with low memory requirements.
Home-page: https://git.wur.nl/hoek008/lmgeo/
Download-URL: https://git.wur.nl/hoek008/lmgeo/-/archive/master/lmgeo-master.tar.gz
Author: Steven Hoek
Author-email: dobedani@gmx.net
License: LGPL
Platform: any
Classifier: Development Status :: 4 - Beta
Classifier: Environment :: Console
Classifier: Intended Audience :: Developers
Classifier: Intended Audience :: Science/Research
Classifier: License :: OSI Approved :: GNU Lesser General Public License v3 (LGPLv3)
Classifier: Natural Language :: English
Classifier: Operating System :: OS Independent
Classifier: Programming Language :: Python
Classifier: Topic :: Scientific/Engineering
License-File: LICENSE
Requires-Dist: pyshp (>=2.1.0)
Requires-Dist: pyproj (>=1.9.5.1)
Requires-Dist: numpy (>=1.14.3)
Requires-Dist: tifffile (>=2019.3.18)
Requires-Dist: tables (>=3.5.2)
Requires-Dist: pylibtiff (>=0.4.2)
Requires-Dist: pygeopkg (>=0.1.2)
Requires-Dist: delaunay-triangulation (>=1.0.3)
Provides-Extra: netcdf4
Requires-Dist: netCDF4 ; extra == 'netcdf4'
